robin_logs/__init__.py
robin_logs/cleanup.py
robin_logs/config.py
robin_logs/core.py
robin_logs/reader.py
robin_logs/routes.py
robin_logs-0.1.0.dist-info/licenses/LICENSE
robin_logs-0.1.0.dist-info/METADATA
robin_logs-0.1.0.dist-info/WHEEL
robin_logs-0.1.0.dist-info/top_level.txt
robin_logs-0.1.0.dist-info/RECORD
