Metadata-Version: 2.4
Name: robin-logs
Version: 0.1.0
Summary: Sistema de logs estructurado y desacoplado para FastAPI
Home-page: https://github.com/yourorg/robin-logs
Author: Robin Team
Author-email: Robin Team <team@robin.com>
License: MIT
Project-URL: Homepage, https://github.com/yourorg/robin-logs
Project-URL: Documentation, https://github.com/yourorg/robin-logs/wiki
Project-URL: Repository, https://github.com/yourorg/robin-logs
Keywords: logging,fastapi,structured-logging,log-rotation
Classifier: Development Status :: 4 - Beta
Classifier: Intended Audience :: Developers
Classifier: Topic :: Software Development :: Libraries :: Python Modules
Classifier: Topic :: System :: Logging
Classifier: Programming Language :: Python :: 3
Requires-Python: >=3.8
License-File: LICENSE
Requires-Dist: fastapi>=0.100.0
Requires-Dist: python-json-logger>=2.0.0
Provides-Extra: dev
Requires-Dist: pytest>=7.0.0; extra == "dev"
Requires-Dist: pytest-asyncio>=0.21.0; extra == "dev"
Requires-Dist: httpx>=0.24.0; extra == "dev"
Dynamic: author
Dynamic: home-page
Dynamic: license-file
Dynamic: requires-python
